vier_gewinnt_package/__init__.py
vier_gewinnt_package/main.py
vier_gewinnt_package/game_elements/__init__.py
vier_gewinnt_package/game_elements/game.py
vier_gewinnt_package/game_elements/game_piece.py
vier_gewinnt_package/game_elements/game_table.py
vier_gewinnt_package/game_elements/player/__init__.py
vier_gewinnt_package/game_elements/player/player.py
vier_gewinnt_package/game_elements/player/type/__init__.py
vier_gewinnt_package/game_elements/player/type/ai.py
vier_gewinnt_package/game_elements/player/type/human.py
vier_gewinnt_kianbuechner-1.0.1.dist-info/LICENSE.LIC
vier_gewinnt_kianbuechner-1.0.1.dist-info/METADATA
vier_gewinnt_kianbuechner-1.0.1.dist-info/WHEEL
vier_gewinnt_kianbuechner-1.0.1.dist-info/top_level.txt
vier_gewinnt_kianbuechner-1.0.1.dist-info/RECORD
