Metadata-Version: 2.1
Name: vier-gewinnt-kianbuechner
Version: 1.0.1
Summary: Vier Gewinnt mit OOP verbessert
Home-page: https://github.com/kianbuechner/vier_gewinnt
Author: Kian Büchner
Author-email: kbuechner@stud.macromedia.de
Classifier: Programming Language :: Python :: 3
Classifier: License :: OSI Approved :: MIT License
Classifier: Operating System :: OS Independent
Requires-Python: >=3.6
License-File: LICENSE.LIC
